./1501_process.log
./PKG-INFO
./README.md
./language.json
./package_name
./pyproject.toml
./requirements.txt
./trigger.py
./Test Controller/device_test.py.py
iflow_mcp_veenastudio_flstudio-0.1.0.dist-info/METADATA
iflow_mcp_veenastudio_flstudio-0.1.0.dist-info/WHEEL
iflow_mcp_veenastudio_flstudio-0.1.0.dist-info/entry_points.txt
iflow_mcp_veenastudio_flstudio-0.1.0.dist-info/RECORD
