Metadata-Version: 2.4
Name: iflow-mcp-veenastudio-flstudio
Version: 0.1.0
Summary: MCP server that connects Claude to FL Studio
Requires-Python: >=3.8
Requires-Dist: fastmcp>=0.1.0
Requires-Dist: fl-studio-api-stubs>=37.0.1
Requires-Dist: httpx>=0.27.0
Requires-Dist: mido>=1.3.3
Requires-Dist: python-rtmidi>=1.5.8
